Tester.v
module Tester (xOut, yOut, XandYin, XorYin);
	input [1:0] XandYin, XorYin;
	output [1:0] xOut, yOut;
	reg [1:0] xOut, yOut;

	parameter stimDelay = 20;
	initial // Response 
		begin
			$display("\t\t xOut \t yOut \t XandYin XorYin \t Time ");
			$monitor("\t\t %b\t %b \t %b \t %b", xOut, yOut, XandYin, XorYin, $time );

		end

	initial // Stimulus
		begin
			xOut = 2'b00; yOut = 2'b00;
			#stimDelay yOut = 2'b01;
			#stimDelay yOut = 2'b10; 
			#stimDelay yOut = 2'b11;
			#stimDelay xOut = 2'b01; yOut = 2'b00;
			#stimDelay yOut = 2'b01;
			#stimDelay yOut = 2'b10; 
			#stimDelay yOut = 2'b11;
			#stimDelay xOut = 2'b10; yOut = 2'b00;
			#stimDelay yOut = 2'b01;
			#stimDelay yOut = 2'b10; 
			#stimDelay yOut = 2'b11;
			#stimDelay xOut = 2'b11; yOut = 2'b00;
			#stimDelay yOut = 2'b01;
			#stimDelay yOut = 2'b10; 
			#stimDelay yOut = 2'b11;
			#stimDelay 

			#(2*stimDelay);		// needed to see END of simulation
			$finish; 			// finish simulation
		end
endmodule

andOr0.v
// andOr0.v
// Compute the logical AND and OR of inputs A and B. 

module AndOr(AandB, AorB, A, B);
	output [1:0] AandB, AorB; 
	input [1:0] A, B;
	and myAnd [1:0] (AandB[1:0], A[1:0], B[1:0]);
	or myOr [1:0] (AorB[1:0], A[1:0], B[1:0]); 
endmodule

andorTop0.v
// andorTop0.v 
`include "andOr0.v"
`include "Tester.v"

module testBench;
	
	// connect the two modules 
	wire [1:0] X, Y;
	wire [1:0] XandY, XorY;
	
	// declare an instance of the AND module
	AndOr myAndOr (XandY[1:0], XorY[1:0], X[1:0], Y[1:0]);
	
	// declare an instance of the testIt module
	Tester aTester (X[1:0], Y[1:0], XandY[1:0], XorY[1:0]);
	
	// file for gtkwave
	initial 
		begin
			// these two files support gtkwave and are required 
			$dumpfile("andor0.vcd");
			$dumpvars(1, myAndOr); 
		end
endmodule

andor0.vcd
$date
	Sun Jan  8 20:43:31 2017
$end
$version
	Icarus Verilog
$end
$timescale
	1s
$end
$scope module testBench $end
$scope module myAndOr $end
$var wire 2 ! A [1:0] $end
$var wire 2 " AandB [1:0] $end
$var wire 2 # AorB [1:0] $end
$var wire 2 $ B [1:0] $end
$upscope $end
$upscope $end
$enddefinitions $end
#0
$dumpvars
b0 $
b0 #
b0 "
b0 !
$end
#20
b1 #
b1 $
#40
b10 #
b10 $
#60
b11 #
b11 $
#80
b1 #
b0 $
b1 !
#100
b1 "
b1 $
#120
b11 #
b0 "
b10 $
#140
b1 "
b11 $
#160
b10 #
b0 "
b0 $
b10 !
#180
b11 #
b1 $
#200
b10 #
b10 "
b10 $
#220
b11 #
b11 $
#240
b0 "
b0 $
b11 !
#260
b1 "
b1 $
#280
b10 "
b10 $
#300
b11 "
b11 $
